srsinst/uga/__init__.py
srsinst/uga/__main__.py
srsinst/uga/gaslib.dat
srsinst/uga/uga.taskconfig
srsinst/uga/instruments/__init__.py
srsinst/uga/instruments/get_instruments.py
srsinst/uga/instruments/uga100/__init__.py
srsinst/uga/instruments/uga100/components.py
srsinst/uga/instruments/uga100/keys.py
srsinst/uga/instruments/uga100/uga.py
srsinst/uga/tasks/__init__.py
srsinst/uga/tasks/ugamodecontroltask.py
srsinst/uga/tasks/ugamultiplottask.py
srsinst/uga/tasks/ugastatemonitortask.py
srsinst.uga-0.1.0.dist-info/LICENSE
srsinst.uga-0.1.0.dist-info/METADATA
srsinst.uga-0.1.0.dist-info/WHEEL
srsinst.uga-0.1.0.dist-info/entry_points.txt
srsinst.uga-0.1.0.dist-info/top_level.txt
srsinst.uga-0.1.0.dist-info/RECORD
