Metadata-Version: 2.1
Name: srsinst.uga
Version: 0.1.0
Summary: Instrument driver package for Universal Gas Analyzers (UGA) from Stanford Research Systems
Author: Chulhoon Kim
License: MIT license
Project-URL: homepage, https://github.com/thinkSRS/srsinst.uga
Project-URL: repository, https://github.com/thinkSRS/srsinst.uga.git
Keywords: UGA,universal gas analyzer,SRS,Stanford Research Systems
Classifier: Development Status :: 3 - Alpha
Classifier: Intended Audience :: Science/Research
Classifier: License :: OSI Approved :: MIT License
Classifier: Programming Language :: Python :: 3.7
Classifier: Programming Language :: Python :: 3.8
Classifier: Programming Language :: Python :: 3.9
Classifier: Programming Language :: Python :: 3.10
Classifier: Topic :: Scientific/Engineering
Requires-Python: >=3.7
License-File: LICENSE
Requires-Dist: numpy
Requires-Dist: scipy
Requires-Dist: srsgui (>=0.4.0)
Requires-Dist: srsinst.rga (>=0.3.3)
Provides-Extra: full
Requires-Dist: matplotlib (>=3.6.2) ; extra == 'full'
Requires-Dist: pyside6 ; extra == 'full'
